[{"Materia": "CIENCIA DE LOS MATERIALES (401)", "Sabado": "", "Maestro": "HINOJOSA RIVERA MOIS\u00c9S DR.", "Idioma": "INGLES", "Grupo": "1", "Viernes": "", "Lunes": "", "Salon": "1101", "Miercoles": "", "Clave": "400", "Plan": "401", "Jueves": "", "Modalidad": "Semi-Presencial", "Martes": "M1 M2 M3"}, {"Materia": "CIENCIA DE LOS MATERIALES (401)", "Sabado": "M1 M2 M3", "Maestro": "AGUILERA HERN\u00c1NDEZ ROLANDO M.A.", "Idioma": "ESPA\u00d1OL", "Grupo": "1", "Viernes": "", "Lunes": "", "Salon": "7117", "Miercoles": "", "Clave": "400", "Plan": "401", "Jueves": "", "Modalidad": "Presencial", "Martes": ""}, {"Materia": "CIENCIA DE LOS MATERIALES (401)", "Sabado": "M4 M5 M6", "Maestro": "AGUILERA HERN\u00c1NDEZ ROLANDO M.A.", "Idioma": "ESPA\u00d1OL", "Grupo": "2", "Viernes": "", "Lunes": "", "Salon": "1105", "Miercoles": "", "Clave": "400", "Plan": "401", "Jueves": "", "Modalidad": "Presencial", "Martes": ""}, {"Materia": "CIENCIA DE LOS MATERIALES (401)", "Sabado": "", "Maestro": "CH\u00c1VEZ GUERRERO LEONARDO DR.", "Idioma": "ESPA\u00d1OL", "Grupo": "2", "Viernes": "", "Lunes": "", "Salon": "7116", "Miercoles": "", "Clave": "400", "Plan": "401", "Jueves": "", "Modalidad": "Presencial", "Martes": "M1 M2 M3"}, {"Materia": "CIENCIA DE LOS MATERIALES (401)", "Sabado": "", "Maestro": "GONZ\u00c1LEZ CARRANZA YADIRA M.C.", "Idioma": "ESPA\u00d1OL", "Grupo": "3", "Viernes": "", "Lunes": "", "Salon": "1101", "Miercoles": "", "Clave": "400", "Plan": "401", "Jueves": "M1 M2 M3", "Modalidad": "Presencial", "Martes": ""}, {"Materia": "CIENCIA DE LOS MATERIALES (401)", "Sabado": "M4 M5 M6", "Maestro": "CANALES NA\u00d1EZ CLAUDIA EUGENIA M.C.", "Idioma": "ESPA\u00d1OL", "Grupo": "3", "Viernes": "", "Lunes": "", "Salon": "2201", "Miercoles": "", "Clave": "400", "Plan": "401", "Jueves": "", "Modalidad": "Presencial", "Martes": ""}, {"Materia": "CIENCIA DE LOS MATERIALES (401)", "Sabado": "V1 V2 V3", "Maestro": "AGUILERA HERN\u00c1NDEZ ROLANDO M.A.", "Idioma": "ESPA\u00d1OL", "Grupo": "4", "Viernes": "", "Lunes": "", "Salon": "7117", "Miercoles": "", "Clave": "400", "Plan": "401", "Jueves": "", "Modalidad": "Presencial", "Martes": ""}, {"Materia": "CIENCIA DE LOS MATERIALES (401)", "Sabado": "", "Maestro": "ORTIZ RIVERA LAURA DRA.", "Idioma": "ESPA\u00d1OL", "Grupo": "4", "Viernes": "M2", "Lunes": "M2", "Salon": "7125", "Miercoles": "M2", "Clave": "400", "Plan": "401", "Jueves": "", "Modalidad": "Presencial", "Martes": ""}, {"Materia": "CIENCIA DE LOS MATERIALES (401)", "Sabado": "", "Maestro": "ALDACO CASTA\u00d1EDA JORGE ADRI\u00c1N DR.", "Idioma": "ESPA\u00d1OL", "Grupo": "5", "Viernes": "M2", "Lunes": "M2", "Salon": "1104", "Miercoles": "M2", "Clave": "400", "Plan": "401", "Jueves": "", "Modalidad": "Presencial", "Martes": ""}, {"Materia": "CIENCIA DE LOS MATERIALES (401)", "Sabado": "", "Maestro": "ORTIZ RIVERA LAURA DRA.", "Idioma": "ESPA\u00d1OL", "Grupo": "6", "Viernes": "M3", "Lunes": "M3", "Salon": "7125", "Miercoles": "M3", "Clave": "400", "Plan": "401", "Jueves": "", "Modalidad": "Presencial", "Martes": ""}, {"Materia": "CIENCIA DE LOS MATERIALES (401)", "Sabado": "", "Maestro": "ORTIZ RIVERA LAURA DRA.", "Idioma": "ESPA\u00d1OL", "Grupo": "7", "Viernes": "M4", "Lunes": "M4", "Salon": "7125", "Miercoles": "M4", "Clave": "400", "Plan": "401", "Jueves": "", "Modalidad": "Presencial", "Martes": ""}, {"Materia": "CIENCIA DE LOS MATERIALES (401)", "Sabado": "", "Maestro": "G\u00d3MEZ ZAMORANO LAUREN YOLANDA DRA.", "Idioma": "ESPA\u00d1OL", "Grupo": "8", "Viernes": "", "Lunes": "", "Salon": "3107", "Miercoles": "", "Clave": "400", "Plan": "401", "Jueves": "M4 M5 M6", "Modalidad": "Presencial", "Martes": ""}, {"Materia": "CIENCIA DE LOS MATERIALES (401)", "Sabado": "", "Maestro": "RODR\u00cdGUEZ CASTELLANOS ED\u00c9N AMARAL DR.", "Idioma": "ESPA\u00d1OL", "Grupo": "9", "Viernes": "", "Lunes": "", "Salon": "5303", "Miercoles": "", "Clave": "400", "Plan": "401", "Jueves": "", "Modalidad": "Presencial", "Martes": "M4 M5 M6"}, {"Materia": "CIENCIA DE LOS MATERIALES (401)", "Sabado": "", "Maestro": "DE LA GARZA GARZA MARIBEL DRA.", "Idioma": "INGLES", "Grupo": "10", "Viernes": "", "Lunes": "", "Salon": "7111", "Miercoles": "", "Clave": "400", "Plan": "401", "Jueves": "", "Modalidad": "Semi-Presencial", "Martes": "M4 M5 M6"}, {"Materia": "CIENCIA DE LOS MATERIALES (401)", "Sabado": "", "Maestro": "P\u00c9REZ PATI\u00d1O JUAN ANTONIO M.C.", "Idioma": "ESPA\u00d1OL", "Grupo": "11", "Viernes": "", "Lunes": "", "Salon": "1202", "Miercoles": "", "Clave": "400", "Plan": "401", "Jueves": "", "Modalidad": "Presencial", "Martes": "M4 M5 M6"}, {"Materia": "CIENCIA DE LOS MATERIALES (401)", "Sabado": "", "Maestro": "CABRAL MIRAMONTES JOS\u00c9 \u00c1NGEL DR.", "Idioma": "ESPA\u00d1OL", "Grupo": "12", "Viernes": "", "Lunes": "", "Salon": "7125", "Miercoles": "", "Clave": "400", "Plan": "401", "Jueves": "", "Modalidad": "Presencial", "Martes": "M4 M5 M6"}, {"Materia": "CIENCIA DE LOS MATERIALES (401)", "Sabado": "", "Maestro": "KRISHNAN BIND\u00da DRA.", "Idioma": "ESPA\u00d1OL", "Grupo": "13", "Viernes": "", "Lunes": "", "Salon": "1305", "Miercoles": "", "Clave": "400", "Plan": "401", "Jueves": "", "Modalidad": "Semi-Presencial", "Martes": "M4 M5 M6"}, {"Materia": "CIENCIA DE LOS MATERIALES (401)", "Sabado": "", "Maestro": "KRISHNAN BIND\u00da DRA.", "Idioma": "ESPA\u00d1OL", "Grupo": "13", "Viernes": "", "Lunes": "", "Salon": "1305", "Miercoles": "", "Clave": "400", "Plan": "401", "Jueves": "", "Modalidad": "Semi-Presencial", "Martes": "M4 M5 M6"}, {"Materia": "CIENCIA DE LOS MATERIALES (401)", "Sabado": "V1 V2 V3", "Maestro": "CANALES NA\u00d1EZ CLAUDIA EUGENIA M.C.", "Idioma": "ESPA\u00d1OL", "Grupo": "14", "Viernes": "", "Lunes": "", "Salon": "7119", "Miercoles": "", "Clave": "400", "Plan": "401", "Jueves": "", "Modalidad": "Presencial", "Martes": ""}, {"Materia": "CIENCIA DE LOS MATERIALES (401)", "Sabado": "", "Maestro": "ALMERAYA CALDER\u00d3N FACUNDO DR.", "Idioma": "ESPA\u00d1OL", "Grupo": "15", "Viernes": "", "Lunes": "", "Salon": "3105", "Miercoles": "", "Clave": "400", "Plan": "401", "Jueves": "", "Modalidad": "Presencial", "Martes": "M4 M5 M6"}, {"Materia": "CIENCIA DE LOS MATERIALES (401)", "Sabado": "", "Maestro": "ACOSTA LAND\u00cdN RA\u00daL M.C.", "Idioma": "ESPA\u00d1OL", "Grupo": "16", "Viernes": "", "Lunes": "", "Salon": "7111", "Miercoles": "", "Clave": "400", "Plan": "401", "Jueves": "M4 M5 M6", "Modalidad": "Presencial", "Martes": ""}, {"Materia": "CIENCIA DE LOS MATERIALES (401)", "Sabado": "", "Maestro": "P\u00c9REZ PATI\u00d1O JUAN ANTONIO M.C.", "Idioma": "ESPA\u00d1OL", "Grupo": "17", "Viernes": "", "Lunes": "", "Salon": "1301", "Miercoles": "", "Clave": "400", "Plan": "401", "Jueves": "M4 M5 M6", "Modalidad": "Presencial", "Martes": ""}, {"Materia": "CIENCIA DE LOS MATERIALES (401)", "Sabado": "", "Maestro": "RODR\u00cdGUEZ CASTELLANOS ED\u00c9N AMARAL DR.", "Idioma": "ESPA\u00d1OL", "Grupo": "18", "Viernes": "", "Lunes": "", "Salon": "5303", "Miercoles": "", "Clave": "400", "Plan": "401", "Jueves": "M4 M5 M6", "Modalidad": "Presencial", "Martes": ""}, {"Materia": "CIENCIA DE LOS MATERIALES (401)", "Sabado": "", "Maestro": "CASTILLO RODR\u00cdGUEZ GUADALUPE ALAN DR.", "Idioma": "ESPA\u00d1OL", "Grupo": "19", "Viernes": "", "Lunes": "", "Salon": "7116", "Miercoles": "", "Clave": "400", "Plan": "401", "Jueves": "M4 M5 M6", "Modalidad": "Presencial", "Martes": ""}, {"Materia": "CIENCIA DE LOS MATERIALES (401)", "Sabado": "", "Maestro": "HERN\u00c1NDEZ HERN\u00c1NDEZ MARLA BERENICE DRA.", "Idioma": "ESPA\u00d1OL", "Grupo": "20", "Viernes": "N2", "Lunes": "N2", "Salon": "1202", "Miercoles": "N2", "Clave": "400", "Plan": "401", "Jueves": "", "Modalidad": "Presencial", "Martes": ""}, {"Materia": "CIENCIA DE LOS MATERIALES (401)", "Sabado": "", "Maestro": "HERN\u00c1NDEZ HERN\u00c1NDEZ MARLA BERENICE DRA.", "Idioma": "ESPA\u00d1OL", "Grupo": "20", "Viernes": "N2", "Lunes": "N2", "Salon": "7000", "Miercoles": "N2", "Clave": "400", "Plan": "401", "Jueves": "", "Modalidad": "Presencial", "Martes": ""}, {"Materia": "CIENCIA DE LOS MATERIALES (401)", "Sabado": "", "Maestro": "CANALES NA\u00d1EZ CLAUDIA EUGENIA M.C.", "Idioma": "ESPA\u00d1OL", "Grupo": "21", "Viernes": "", "Lunes": "", "Salon": "7116", "Miercoles": "", "Clave": "400", "Plan": "401", "Jueves": "N4 N5 N6", "Modalidad": "Presencial", "Martes": ""}, {"Materia": "CIENCIA DE LOS MATERIALES (401)", "Sabado": "", "Maestro": "ORTIZ RIVERA LAURA DRA.", "Idioma": "ESPA\u00d1OL", "Grupo": "22", "Viernes": "M5", "Lunes": "M5", "Salon": "7125", "Miercoles": "M5", "Clave": "400", "Plan": "401", "Jueves": "", "Modalidad": "Presencial", "Martes": ""}, {"Materia": "CIENCIA DE LOS MATERIALES (401)", "Sabado": "", "Maestro": "PUENTE ORNELAS RODRIGO DR.", "Idioma": "ESPA\u00d1OL", "Grupo": "23", "Viernes": "V6", "Lunes": "V6", "Salon": "1304", "Miercoles": "V6", "Clave": "400", "Plan": "401", "Jueves": "", "Modalidad": "Presencial", "Martes": ""}, {"Materia": "CIENCIA DE LOS MATERIALES (401)", "Sabado": "", "Maestro": "ORTIZ RIVERA LAURA DRA.", "Idioma": "ESPA\u00d1OL", "Grupo": "24", "Viernes": "M6", "Lunes": "M6", "Salon": "7125", "Miercoles": "M6", "Clave": "400", "Plan": "401", "Jueves": "", "Modalidad": "Presencial", "Martes": ""}, {"Materia": "CIENCIA DE LOS MATERIALES (401)", "Sabado": "", "Maestro": "ORTIZ RIVERA LAURA DRA.", "Idioma": "ESPA\u00d1OL", "Grupo": "26", "Viernes": "V1", "Lunes": "V1", "Salon": "7125", "Miercoles": "V1", "Clave": "400", "Plan": "401", "Jueves": "", "Modalidad": "Presencial", "Martes": ""}, {"Materia": "CIENCIA DE LOS MATERIALES (401)", "Sabado": "", "Maestro": "HERN\u00c1NDEZ HERN\u00c1NDEZ MARLA BERENICE DRA.", "Idioma": "ESPA\u00d1OL", "Grupo": "27", "Viernes": "N3", "Lunes": "N3", "Salon": "2102", "Miercoles": "N3", "Clave": "400", "Plan": "401", "Jueves": "", "Modalidad": "Presencial", "Martes": ""}, {"Materia": "CIENCIA DE LOS MATERIALES (401)", "Sabado": "", "Maestro": "HERN\u00c1NDEZ HERN\u00c1NDEZ MARLA BERENICE DRA.", "Idioma": "ESPA\u00d1OL", "Grupo": "27", "Viernes": "N3", "Lunes": "N3", "Salon": "7000", "Miercoles": "N3", "Clave": "400", "Plan": "401", "Jueves": "", "Modalidad": "Presencial", "Martes": ""}, {"Materia": "CIENCIA DE LOS MATERIALES (401)", "Sabado": "", "Maestro": "P\u00c9REZ PATI\u00d1O JUAN ANTONIO M.C.", "Idioma": "ESPA\u00d1OL", "Grupo": "29", "Viernes": "", "Lunes": "", "Salon": "1202", "Miercoles": "", "Clave": "400", "Plan": "401", "Jueves": "", "Modalidad": "Presencial", "Martes": "V1 V2 V3"}, {"Materia": "CIENCIA DE LOS MATERIALES (401)", "Sabado": "", "Maestro": "MOHAMED NORIEGA NASSER DR.", "Idioma": "ESPA\u00d1OL", "Grupo": "30", "Viernes": "", "Lunes": "", "Salon": "1204", "Miercoles": "", "Clave": "400", "Plan": "401", "Jueves": "", "Modalidad": "Presencial", "Martes": "M4 M5 M6"}, {"Materia": "CIENCIA DE LOS MATERIALES (401)", "Sabado": "", "Maestro": "P\u00c9REZ PATI\u00d1O JUAN ANTONIO M.C.", "Idioma": "ESPA\u00d1OL", "Grupo": "31", "Viernes": "", "Lunes": "", "Salon": "1301", "Miercoles": "", "Clave": "400", "Plan": "401", "Jueves": "V1 V2 V3", "Modalidad": "Presencial", "Martes": ""}, {"Materia": "CIENCIA DE LOS MATERIALES (401)", "Sabado": "V1 V2 V3", "Maestro": "CANALES NA\u00d1EZ ADRI\u00c1N ANTONIO M.C.", "Idioma": "ESPA\u00d1OL", "Grupo": "32", "Viernes": "", "Lunes": "", "Salon": "7111", "Miercoles": "", "Clave": "400", "Plan": "401", "Jueves": "", "Modalidad": "Presencial", "Martes": ""}, {"Materia": "CIENCIA DE LOS MATERIALES (401)", "Sabado": "", "Maestro": "ORTIZ RIVERA LAURA DRA.", "Idioma": "ESPA\u00d1OL", "Grupo": "33", "Viernes": "V2", "Lunes": "V2", "Salon": "7125", "Miercoles": "V2", "Clave": "400", "Plan": "401", "Jueves": "", "Modalidad": "Presencial", "Martes": ""}, {"Materia": "CIENCIA DE LOS MATERIALES (401)", "Sabado": "", "Maestro": "HERN\u00c1NDEZ HERN\u00c1NDEZ MARLA BERENICE DRA.", "Idioma": "ESPA\u00d1OL", "Grupo": "34", "Viernes": "N6", "Lunes": "N6", "Salon": "1105", "Miercoles": "N6", "Clave": "400", "Plan": "401", "Jueves": "", "Modalidad": "Presencial", "Martes": ""}, {"Materia": "CIENCIA DE LOS MATERIALES (401)", "Sabado": "", "Maestro": "G\u00d3MEZ ZAMORANO LAUREN YOLANDA DRA.", "Idioma": "ESPA\u00d1OL", "Grupo": "36", "Viernes": "", "Lunes": "", "Salon": "3107", "Miercoles": "", "Clave": "400", "Plan": "401", "Jueves": "V1 V2 V3", "Modalidad": "Presencial", "Martes": ""}, {"Materia": "CIENCIA DE LOS MATERIALES (401)", "Sabado": "", "Maestro": "V\u00c1ZQUEZ RODR\u00cdGUEZ SOF\u00cdA DRA.", "Idioma": "ESPA\u00d1OL", "Grupo": "38", "Viernes": "", "Lunes": "", "Salon": "7116", "Miercoles": "", "Clave": "400", "Plan": "401", "Jueves": "", "Modalidad": "Presencial", "Martes": "V1 V2 V3"}, {"Materia": "CIENCIA DE LOS MATERIALES (401)", "Sabado": "", "Maestro": "GARZA NAVARRO MARCO ANTONIO DR.", "Idioma": "ESPA\u00d1OL", "Grupo": "39", "Viernes": "", "Lunes": "", "Salon": "1101", "Miercoles": "", "Clave": "400", "Plan": "401", "Jueves": "", "Modalidad": "Presencial", "Martes": "V4 V5 V6"}, {"Materia": "CIENCIA DE LOS MATERIALES (401)", "Sabado": "", "Maestro": "DE LA GARZA GARZA MARIBEL DRA.", "Idioma": "INGLES", "Grupo": "40", "Viernes": "", "Lunes": "", "Salon": "7125", "Miercoles": "", "Clave": "400", "Plan": "401", "Jueves": "", "Modalidad": "Semi-Presencial", "Martes": "V4 V5 V6"}, {"Materia": "CIENCIA DE LOS MATERIALES (401)", "Sabado": "", "Maestro": "MORENO CORTEZ IV\u00c1N ELEAZAR DR.", "Idioma": "ESPA\u00d1OL", "Grupo": "41", "Viernes": "", "Lunes": "", "Salon": "1205", "Miercoles": "", "Clave": "400", "Plan": "401", "Jueves": "V4 V5 V6", "Modalidad": "Presencial", "Martes": ""}, {"Materia": "CIENCIA DE LOS MATERIALES (401)", "Sabado": "", "Maestro": "GONZ\u00c1LEZ CARRANZA YADIRA M.C.", "Idioma": "ESPA\u00d1OL", "Grupo": "42", "Viernes": "", "Lunes": "", "Salon": "7118", "Miercoles": "", "Clave": "400", "Plan": "401", "Jueves": "", "Modalidad": "Presencial", "Martes": "V4 V5 V6"}, {"Materia": "CIENCIA DE LOS MATERIALES (401)", "Sabado": "", "Maestro": "GONZ\u00c1LEZ CARRANZA YADIRA M.C.", "Idioma": "ESPA\u00d1OL", "Grupo": "43", "Viernes": "", "Lunes": "", "Salon": "7118", "Miercoles": "", "Clave": "400", "Plan": "401", "Jueves": "V4 V5 V6", "Modalidad": "Presencial", "Martes": ""}, {"Materia": "CIENCIA DE LOS MATERIALES (401)", "Sabado": "", "Maestro": "SOLACHE MENDOZA J. JES\u00daS M.C.", "Idioma": "ESPA\u00d1OL", "Grupo": "44", "Viernes": "V6", "Lunes": "V6", "Salon": "7120", "Miercoles": "V6", "Clave": "400", "Plan": "401", "Jueves": "", "Modalidad": "Presencial", "Martes": ""}, {"Materia": "CIENCIA DE LOS MATERIALES (401)", "Sabado": "", "Maestro": "SOLACHE MENDOZA J. JES\u00daS M.C.", "Idioma": "ESPA\u00d1OL", "Grupo": "45", "Viernes": "N1", "Lunes": "N1", "Salon": "7119", "Miercoles": "N1", "Clave": "400", "Plan": "401", "Jueves": "", "Modalidad": "Presencial", "Martes": ""}, {"Materia": "CIENCIA DE LOS MATERIALES (401)", "Sabado": "", "Maestro": "CABALLERO HERN\u00c1NDEZ MANUEL SERGIO M.I.", "Idioma": "ESPA\u00d1OL", "Grupo": "46", "Viernes": "N1", "Lunes": "N1", "Salon": "7120", "Miercoles": "N1", "Clave": "400", "Plan": "401", "Jueves": "", "Modalidad": "Presencial", "Martes": ""}, {"Materia": "CIENCIA DE LOS MATERIALES (401)", "Sabado": "", "Maestro": "SOLACHE MENDOZA J. JES\u00daS M.C.", "Idioma": "ESPA\u00d1OL", "Grupo": "47", "Viernes": "", "Lunes": "", "Salon": "7111", "Miercoles": "", "Clave": "400", "Plan": "401", "Jueves": "", "Modalidad": "Presencial", "Martes": "N1 N2 N3"}, {"Materia": "CIENCIA DE LOS MATERIALES (401)", "Sabado": "", "Maestro": "SEP\u00daLVEDA GUZM\u00c1N SELENE DRA.", "Idioma": "ESPA\u00d1OL", "Grupo": "48", "Viernes": "", "Lunes": "", "Salon": "3301", "Miercoles": "", "Clave": "400", "Plan": "401", "Jueves": "", "Modalidad": "Presencial", "Martes": "N4 N5 N6"}, {"Materia": "CIENCIA DE LOS MATERIALES (401)", "Sabado": "", "Maestro": "CASTILLO RODR\u00cdGUEZ GUADALUPE ALAN DR.", "Idioma": "ESPA\u00d1OL", "Grupo": "49", "Viernes": "", "Lunes": "", "Salon": "7118", "Miercoles": "", "Clave": "400", "Plan": "401", "Jueves": "N1 N2 N3", "Modalidad": "Presencial", "Martes": ""}, {"Materia": "CIENCIA DE LOS MATERIALES (401)", "Sabado": "", "Maestro": "SOLACHE MENDOZA J. JES\u00daS M.C.", "Idioma": "ESPA\u00d1OL", "Grupo": "50", "Viernes": "N2", "Lunes": "N2", "Salon": "7118", "Miercoles": "N2", "Clave": "400", "Plan": "401", "Jueves": "", "Modalidad": "Presencial", "Martes": ""}, {"Materia": "CIENCIA DE LOS MATERIALES (401)", "Sabado": "", "Maestro": "SOLACHE MENDOZA J. JES\u00daS M.C.", "Idioma": "ESPA\u00d1OL", "Grupo": "51", "Viernes": "N4", "Lunes": "N4", "Salon": "7120", "Miercoles": "N4", "Clave": "400", "Plan": "401", "Jueves": "", "Modalidad": "Presencial", "Martes": ""}, {"Materia": "CIENCIA DE LOS MATERIALES (401)", "Sabado": "", "Maestro": "MAR\u00cdN S\u00c1NCHEZ ISMAEL M.C.", "Idioma": "ESPA\u00d1OL", "Grupo": "52", "Viernes": "N4", "Lunes": "N4", "Salon": "9304", "Miercoles": "N4", "Clave": "400", "Plan": "401", "Jueves": "", "Modalidad": "Presencial", "Martes": ""}, {"Materia": "CIENCIA DE LOS MATERIALES (401)", "Sabado": "", "Maestro": "CANALES NA\u00d1EZ CLAUDIA EUGENIA M.C.", "Idioma": "ESPA\u00d1OL", "Grupo": "53", "Viernes": "", "Lunes": "", "Salon": "7119", "Miercoles": "", "Clave": "400", "Plan": "401", "Jueves": "", "Modalidad": "Presencial", "Martes": "N4 N5 N6"}, {"Materia": "CIENCIA DE LOS MATERIALES (401)", "Sabado": "", "Maestro": "GARC\u00cdA S\u00c1NCHEZ EDGAR OMAR DR.", "Idioma": "ESPA\u00d1OL", "Grupo": "54", "Viernes": "", "Lunes": "", "Salon": "1103", "Miercoles": "", "Clave": "400", "Plan": "401", "Jueves": "M4 M5 M6", "Modalidad": "Presencial", "Martes": ""}, {"Materia": "CIENCIA DE LOS MATERIALES (401)", "Sabado": "", "Maestro": "SOLACHE MENDOZA J. JES\u00daS M.C.", "Idioma": "ESPA\u00d1OL", "Grupo": "55", "Viernes": "N5", "Lunes": "N5", "Salon": "7120", "Miercoles": "N5", "Clave": "400", "Plan": "401", "Jueves": "", "Modalidad": "Presencial", "Martes": ""}, {"Materia": "CIENCIA DE LOS MATERIALES (401)", "Sabado": "", "Maestro": "V\u00c1ZQUEZ RODR\u00cdGUEZ SOF\u00cdA DRA.", "Idioma": "ESPA\u00d1OL", "Grupo": "56", "Viernes": "", "Lunes": "", "Salon": "7118", "Miercoles": "", "Clave": "400", "Plan": "401", "Jueves": "", "Modalidad": "Presencial", "Martes": "M4 M5 M6"}, {"Materia": "CIENCIA DE LOS MATERIALES (401)", "Sabado": "", "Maestro": "ALDACO CASTA\u00d1EDA JORGE ADRI\u00c1N DR.", "Idioma": "ESPA\u00d1OL", "Grupo": "57", "Viernes": "M3", "Lunes": "M3", "Salon": "7116", "Miercoles": "M3", "Clave": "400", "Plan": "401", "Jueves": "", "Modalidad": "Presencial", "Martes": ""}, {"Materia": "CIENCIA DE LOS MATERIALES (401)", "Sabado": "", "Maestro": "MORENO CORTEZ IV\u00c1N ELEAZAR DR.", "Idioma": "ESPA\u00d1OL", "Grupo": "58", "Viernes": "", "Lunes": "", "Salon": "3205", "Miercoles": "", "Clave": "400", "Plan": "401", "Jueves": "N1 N2 N3", "Modalidad": "Presencial", "Martes": ""}, {"Materia": "CIENCIA DE LOS MATERIALES (401)", "Sabado": "", "Maestro": "RODR\u00cdGUEZ GARC\u00cdA \u00c1NGEL MARIO ING.", "Idioma": "ESPA\u00d1OL", "Grupo": "99", "Viernes": "", "Lunes": "", "Salon": "lin1", "Miercoles": "V5 V6 N1", "Clave": "400", "Plan": "401", "Jueves": "", "Modalidad": "Presencial", "Martes": ""}]