[{"Materia": "LAB.DE ALGORITMOS COMPUTACIONALES (401)", "Sabado": "", "Maestro": "DE LE\u00d3N CEPEDA PABLO EUSEBIO ING.", "Idioma": "ESPA\u00d1OL", "Grupo": "1", "Viernes": "", "Lunes": "", "Salon": "4212", "Miercoles": "", "Clave": "839", "Plan": "401", "Jueves": "", "Modalidad": "Presencial", "Martes": "M1 M2"}, {"Materia": "LAB.DE ALGORITMOS COMPUTACIONALES (401)", "Sabado": "", "Maestro": "DE LE\u00d3N CEPEDA PABLO EUSEBIO ING.", "Idioma": "ESPA\u00d1OL", "Grupo": "2", "Viernes": "", "Lunes": "", "Salon": "4109", "Miercoles": "", "Clave": "839", "Plan": "401", "Jueves": "M1 M2", "Modalidad": "Presencial", "Martes": ""}, {"Materia": "LAB.DE ALGORITMOS COMPUTACIONALES (401)", "Sabado": "", "Maestro": "PORRAS V\u00c1ZQUEZ KARLA NATHALI M.A.", "Idioma": "ESPA\u00d1OL", "Grupo": "3", "Viernes": "", "Lunes": "", "Salon": "4108", "Miercoles": "", "Clave": "839", "Plan": "401", "Jueves": "V1 V2", "Modalidad": "Presencial", "Martes": ""}, {"Materia": "LAB.DE ALGORITMOS COMPUTACIONALES (401)", "Sabado": "", "Maestro": "PORRAS V\u00c1ZQUEZ KARLA NATHALI M.A.", "Idioma": "ESPA\u00d1OL", "Grupo": "4", "Viernes": "", "Lunes": "", "Salon": "4109", "Miercoles": "", "Clave": "839", "Plan": "401", "Jueves": "V5 V6", "Modalidad": "Presencial", "Martes": ""}]